person_generate/__init__.py
person_generate/altura.py
person_generate/cpf.py
person_generate/data_de_nascimento.py
person_generate/nome.py
person_generate/peso.py
person_generate/pessoa_F.py
person_generate/pessoa_M.py
person_generate/telefone.py
person_generate-1.3.0.dist-info/METADATA
person_generate-1.3.0.dist-info/WHEEL
person_generate-1.3.0.dist-info/top_level.txt
person_generate-1.3.0.dist-info/RECORD
